{"events":[{"params":[1],"name":"Camera Movement","time":0},{"params":[0],"name":"Camera Movement","time":3200},{"params":[1],"name":"Camera Movement","time":9600},{"params":[0],"name":"Camera Movement","time":16000},{"params":[0,true],"name":"Alt Animation Toggle","time":16000},{"params":[1],"name":"Camera Movement","time":22400},{"params":[0],"name":"Camera Movement","time":28800},{"params":[0,false],"name":"Alt Animation Toggle","time":28800},{"params":[1],"name":"Camera Movement","time":35200},{"params":[0],"name":"Camera Movement","time":41600},{"params":[0,true],"name":"Alt Animation Toggle","time":41600},{"params":[1],"name":"Camera Movement","time":43200},{"params":[0],"name":"Camera Movement","time":44800},{"params":[1],"name":"Camera Movement","time":46400},{"params":[0],"name":"Camera Movement","time":48000},{"params":[0,false],"name":"Alt Animation Toggle","time":48000},{"params":[1],"name":"Camera Movement","time":54400},{"params":[0],"name":"Camera Movement","time":60800},{"params":[0,true],"name":"Alt Animation Toggle","time":60800},{"params":[1],"name":"Camera Movement","time":64000},{"params":[0],"name":"Camera Movement","time":67200},{"params":[1],"name":"Camera Movement","time":70400},{"params":[0,false],"name":"Alt Animation Toggle","time":73600},{"params":[0],"name":"Camera Movement","time":86400},{"params":[0,true],"name":"Alt Animation Toggle","time":86400},{"params":[1],"name":"Camera Movement","time":88000},{"params":[0],"name":"Camera Movement","time":89600},{"params":[1],"name":"Camera Movement","time":91200}],"scrollSpeed":1.9,"strumLines":[{"visible":true,"notes":[{"id":3,"sLen":0,"time":3400,"type":0},{"id":1,"sLen":0,"time":3500,"type":0},{"id":3,"sLen":0,"time":3600,"type":0},{"id":3,"sLen":0,"time":4000,"type":0},{"id":3,"sLen":0,"time":4200,"type":0},{"id":0,"sLen":0,"time":4400,"type":0},{"id":2,"sLen":0,"time":4600,"type":0},{"id":3,"sLen":0,"time":5000,"type":0},{"id":0,"sLen":0,"time":5100,"type":0},{"id":3,"sLen":0,"time":5200,"type":0},{"id":3,"sLen":0,"time":5400,"type":0},{"id":1,"sLen":0,"time":5600,"type":0},{"id":2,"sLen":0,"time":5800,"type":0},{"id":0,"sLen":0,"time":5900,"type":0},{"id":3,"sLen":0,"time":6000,"type":0},{"id":2,"sLen":0,"time":6200,"type":0},{"id":3,"sLen":0,"time":6600,"type":0},{"id":1,"sLen":0,"time":6700,"type":0},{"id":3,"sLen":0,"time":6800,"type":0},{"id":3,"sLen":0,"time":7200,"type":0},{"id":3,"sLen":0,"time":7400,"type":0},{"id":0,"sLen":0,"time":7600,"type":0},{"id":2,"sLen":0,"time":7800,"type":0},{"id":3,"sLen":0,"time":8200,"type":0},{"id":0,"sLen":0,"time":8300,"type":0},{"id":3,"sLen":0,"time":8400,"type":0},{"id":3,"sLen":0,"time":8600,"type":0},{"id":1,"sLen":0,"time":8800,"type":0},{"id":2,"sLen":0,"time":9000,"type":0},{"id":0,"sLen":0,"time":9100,"type":0},{"id":3,"sLen":0,"time":9200,"type":0},{"id":2,"sLen":0,"time":9400,"type":0},{"id":2,"sLen":0,"time":16000,"type":0},{"id":0,"sLen":0,"time":16100,"type":0},{"id":2,"sLen":0,"time":16200,"type":0},{"id":0,"sLen":0,"time":16300,"type":0},{"id":1,"sLen":0,"time":16400,"type":0},{"id":3,"sLen":300,"time":16500,"type":0},{"id":0,"sLen":400,"time":16800,"type":0},{"id":1,"sLen":0,"time":17200,"type":0},{"id":3,"sLen":0,"time":17400,"type":0},{"id":3,"sLen":0,"time":17600,"type":0},{"id":2,"sLen":0,"time":17800,"type":0},{"id":2,"sLen":0,"time":18200,"type":0},{"id":2,"sLen":0,"time":18600,"type":0},{"id":0,"sLen":0,"time":18700,"type":0},{"id":1,"sLen":0,"time":18800,"type":0},{"id":3,"sLen":600,"time":19000,"type":0},{"id":2,"sLen":0,"time":19600,"type":0},{"id":1,"sLen":0,"time":20000,"type":0},{"id":1,"sLen":0,"time":20200,"type":0},{"id":3,"sLen":0,"time":20400,"type":0},{"id":0,"sLen":300,"time":20600,"type":0},{"id":0,"sLen":0,"time":21000,"type":0},{"id":3,"sLen":0,"time":21400,"type":0},{"id":1,"sLen":0,"time":21500,"type":0},{"id":3,"sLen":0,"time":21600,"type":0},{"id":3,"sLen":0,"time":21800,"type":0},{"id":2,"sLen":400,"time":22000,"type":0},{"id":0,"sLen":400,"time":22400,"type":0},{"id":2,"sLen":0,"time":29000,"type":0},{"id":0,"sLen":0,"time":29200,"type":0},{"id":1,"sLen":0,"time":29400,"type":0},{"id":2,"sLen":0,"time":29500,"type":0},{"id":3,"sLen":0,"time":29600,"type":0},{"id":0,"sLen":0,"time":29700,"type":0},{"id":1,"sLen":0,"time":29800,"type":0},{"id":0,"sLen":0,"time":30000,"type":0},{"id":1,"sLen":0,"time":30200,"type":0},{"id":2,"sLen":0,"time":30300,"type":0},{"id":3,"sLen":0,"time":30400,"type":0},{"id":0,"sLen":0,"time":30500,"type":0},{"id":1,"sLen":0,"time":30600,"type":0},{"id":0,"sLen":0,"time":30800,"type":0},{"id":1,"sLen":0,"time":31000,"type":0},{"id":2,"sLen":0,"time":31100,"type":0},{"id":3,"sLen":0,"time":31200,"type":0},{"id":0,"sLen":0,"time":31300,"type":0},{"id":1,"sLen":0,"time":31400,"type":0},{"id":3,"sLen":0,"time":31600,"type":0},{"id":2,"sLen":0,"time":31700,"type":0},{"id":1,"sLen":0,"time":31800,"type":0},{"id":2,"sLen":0,"time":32000,"type":0},{"id":2,"sLen":0,"time":32200,"type":0},{"id":0,"sLen":0,"time":32400,"type":0},{"id":1,"sLen":0,"time":32600,"type":0},{"id":2,"sLen":0,"time":32700,"type":0},{"id":3,"sLen":0,"time":32800,"type":0},{"id":0,"sLen":0,"time":32900,"type":0},{"id":1,"sLen":0,"time":33000,"type":0},{"id":0,"sLen":0,"time":33200,"type":0},{"id":1,"sLen":0,"time":33400,"type":0},{"id":2,"sLen":0,"time":33500,"type":0},{"id":3,"sLen":0,"time":33600,"type":0},{"id":0,"sLen":0,"time":33700,"type":0},{"id":1,"sLen":0,"time":33800,"type":0},{"id":0,"sLen":0,"time":34000,"type":0},{"id":3,"sLen":0,"time":34200,"type":0},{"id":0,"sLen":0,"time":34400,"type":0},{"id":2,"sLen":0,"time":34500,"type":0},{"id":3,"sLen":0,"time":34600,"type":0},{"id":1,"sLen":0,"time":34700,"type":0},{"id":2,"sLen":0,"time":34800,"type":0},{"id":3,"sLen":0,"time":34900,"type":0},{"id":0,"sLen":0,"time":35000,"type":0},{"id":2,"sLen":400,"time":35200,"type":0},{"id":0,"sLen":0,"time":41700,"type":0},{"id":3,"sLen":0,"time":41800,"type":0},{"id":2,"sLen":0,"time":42000,"type":0},{"id":0,"sLen":0,"time":42200,"type":0},{"id":3,"sLen":0,"time":42400,"type":0},{"id":2,"sLen":0,"time":42500,"type":0},{"id":1,"sLen":0,"time":42600,"type":0},{"id":2,"sLen":0,"time":42800,"type":0},{"id":1,"sLen":0,"time":42900,"type":0},{"id":0,"sLen":0,"time":43000,"type":0},{"id":2,"sLen":400,"time":43200,"type":0},{"id":0,"sLen":0,"time":44900,"type":0},{"id":3,"sLen":0,"time":45000,"type":0},{"id":2,"sLen":0,"time":45200,"type":0},{"id":3,"sLen":0,"time":45300,"type":0},{"id":0,"sLen":0,"time":45400,"type":0},{"id":1,"sLen":0,"time":45500,"type":0},{"id":3,"sLen":0,"time":45600,"type":0},{"id":2,"sLen":0,"time":45700,"type":0},{"id":1,"sLen":0,"time":45800,"type":0},{"id":2,"sLen":0,"time":46000,"type":0},{"id":1,"sLen":0,"time":46100,"type":0},{"id":0,"sLen":0,"time":46200,"type":0},{"id":2,"sLen":400,"time":46400,"type":0},{"id":3,"sLen":0,"time":48200,"type":0},{"id":0,"sLen":0,"time":48300,"type":0},{"id":3,"sLen":0,"time":48400,"type":0},{"id":3,"sLen":0,"time":48800,"type":0},{"id":1,"sLen":0,"time":48900,"type":0},{"id":3,"sLen":0,"time":49000,"type":0},{"id":3,"sLen":0,"time":49200,"type":0},{"id":2,"sLen":0,"time":49300,"type":0},{"id":0,"sLen":0,"time":49400,"type":0},{"id":1,"sLen":0,"time":49500,"type":0},{"id":3,"sLen":0,"time":49800,"type":0},{"id":0,"sLen":0,"time":49900,"type":0},{"id":3,"sLen":0,"time":50000,"type":0},{"id":3,"sLen":0,"time":50200,"type":0},{"id":1,"sLen":0,"time":50400,"type":0},{"id":0,"sLen":0,"time":50500,"type":0},{"id":1,"sLen":0,"time":50600,"type":0},{"id":3,"sLen":0,"time":50800,"type":0},{"id":2,"sLen":0,"time":50900,"type":0},{"id":0,"sLen":0,"time":51000,"type":0},{"id":3,"sLen":0,"time":51400,"type":0},{"id":0,"sLen":0,"time":51500,"type":0},{"id":3,"sLen":0,"time":51600,"type":0},{"id":3,"sLen":0,"time":52000,"type":0},{"id":1,"sLen":0,"time":52100,"type":0},{"id":3,"sLen":0,"time":52200,"type":0},{"id":3,"sLen":0,"time":52400,"type":0},{"id":2,"sLen":0,"time":52500,"type":0},{"id":0,"sLen":0,"time":52600,"type":0},{"id":1,"sLen":0,"time":52700,"type":0},{"id":3,"sLen":0,"time":53000,"type":0},{"id":0,"sLen":0,"time":53100,"type":0},{"id":3,"sLen":0,"time":53200,"type":0},{"id":3,"sLen":0,"time":53400,"type":0},{"id":1,"sLen":0,"time":53600,"type":0},{"id":0,"sLen":0,"time":53700,"type":0},{"id":1,"sLen":0,"time":53800,"type":0},{"id":3,"sLen":0,"time":54000,"type":0},{"id":2,"sLen":0,"time":54100,"type":0},{"id":0,"sLen":0,"time":54200,"type":0},{"id":0,"sLen":0,"time":60800,"type":0},{"id":3,"sLen":0,"time":60900,"type":0},{"id":2,"sLen":0,"time":61000,"type":0},{"id":3,"sLen":0,"time":61200,"type":0},{"id":1,"sLen":0,"time":61300,"type":0},{"id":0,"sLen":0,"time":61400,"type":0},{"id":3,"sLen":0,"time":61600,"type":0},{"id":0,"sLen":0,"time":61800,"type":0},{"id":1,"sLen":0,"time":62000,"type":0},{"id":2,"sLen":0,"time":62200,"type":0},{"id":0,"sLen":0,"time":62400,"type":0},{"id":3,"sLen":0,"time":62500,"type":0},{"id":2,"sLen":0,"time":62600,"type":0},{"id":1,"sLen":0,"time":62800,"type":0},{"id":2,"sLen":0,"time":62900,"type":0},{"id":3,"sLen":0,"time":63000,"type":0},{"id":0,"sLen":0,"time":63200,"type":0},{"id":2,"sLen":0,"time":63400,"type":0},{"id":0,"sLen":400,"time":63600,"type":0},{"id":1,"sLen":0,"time":67200,"type":0},{"id":1,"sLen":0,"time":67300,"type":0},{"id":2,"sLen":0,"time":67400,"type":0},{"id":3,"sLen":0,"time":67600,"type":0},{"id":0,"sLen":0,"time":67800,"type":0},{"id":2,"sLen":0,"time":68000,"type":0},{"id":0,"sLen":0,"time":68200,"type":0},{"id":1,"sLen":0,"time":68400,"type":0},{"id":0,"sLen":0,"time":68500,"type":0},{"id":1,"sLen":0,"time":68600,"type":0},{"id":3,"sLen":0,"time":68700,"type":0},{"id":0,"sLen":0,"time":68800,"type":0},{"id":3,"sLen":0,"time":68900,"type":0},{"id":1,"sLen":0,"time":69000,"type":0},{"id":2,"sLen":0,"time":69200,"type":0},{"id":0,"sLen":0,"time":69300,"type":0},{"id":2,"sLen":0,"time":69400,"type":0},{"id":3,"sLen":0,"time":69500,"type":0},{"id":1,"sLen":0,"time":69600,"type":0},{"id":2,"sLen":0,"time":69700,"type":0},{"id":0,"sLen":0,"time":69800,"type":0},{"id":2,"sLen":300,"time":70000,"type":0},{"id":2,"sLen":0,"time":73800,"type":0},{"id":0,"sLen":0,"time":74000,"type":0},{"id":1,"sLen":0,"time":74200,"type":0},{"id":2,"sLen":0,"time":74300,"type":0},{"id":3,"sLen":0,"time":74400,"type":0},{"id":0,"sLen":0,"time":74500,"type":0},{"id":1,"sLen":0,"time":74600,"type":0},{"id":0,"sLen":0,"time":74800,"type":0},{"id":1,"sLen":0,"time":75000,"type":0},{"id":2,"sLen":0,"time":75100,"type":0},{"id":3,"sLen":0,"time":75200,"type":0},{"id":0,"sLen":0,"time":75300,"type":0},{"id":1,"sLen":0,"time":75400,"type":0},{"id":0,"sLen":0,"time":75600,"type":0},{"id":1,"sLen":0,"time":75800,"type":0},{"id":2,"sLen":0,"time":75900,"type":0},{"id":3,"sLen":0,"time":76000,"type":0},{"id":0,"sLen":0,"time":76100,"type":0},{"id":1,"sLen":0,"time":76200,"type":0},{"id":3,"sLen":0,"time":76400,"type":0},{"id":2,"sLen":0,"time":76500,"type":0},{"id":1,"sLen":0,"time":76600,"type":0},{"id":2,"sLen":0,"time":76800,"type":0},{"id":2,"sLen":0,"time":77000,"type":0},{"id":0,"sLen":0,"time":77200,"type":0},{"id":1,"sLen":0,"time":77400,"type":0},{"id":2,"sLen":0,"time":77500,"type":0},{"id":3,"sLen":0,"time":77600,"type":0},{"id":0,"sLen":0,"time":77700,"type":0},{"id":1,"sLen":0,"time":77800,"type":0},{"id":0,"sLen":0,"time":78000,"type":0},{"id":1,"sLen":0,"time":78200,"type":0},{"id":2,"sLen":0,"time":78300,"type":0},{"id":3,"sLen":0,"time":78400,"type":0},{"id":0,"sLen":0,"time":78500,"type":0},{"id":1,"sLen":0,"time":78600,"type":0},{"id":0,"sLen":0,"time":78800,"type":0},{"id":3,"sLen":0,"time":79000,"type":0},{"id":0,"sLen":0,"time":79200,"type":0},{"id":2,"sLen":0,"time":79300,"type":0},{"id":3,"sLen":0,"time":79400,"type":0},{"id":1,"sLen":0,"time":79500,"type":0},{"id":2,"sLen":0,"time":79600,"type":0},{"id":3,"sLen":0,"time":79700,"type":0},{"id":0,"sLen":0,"time":79800,"type":0},{"id":2,"sLen":400,"time":80000,"type":0},{"id":0,"sLen":0,"time":86500,"type":0},{"id":3,"sLen":0,"time":86600,"type":0},{"id":2,"sLen":0,"time":86800,"type":0},{"id":0,"sLen":0,"time":87000,"type":0},{"id":3,"sLen":0,"time":87200,"type":0},{"id":2,"sLen":0,"time":87300,"type":0},{"id":1,"sLen":0,"time":87400,"type":0},{"id":2,"sLen":0,"time":87600,"type":0},{"id":1,"sLen":0,"time":87700,"type":0},{"id":0,"sLen":0,"time":87800,"type":0},{"id":2,"sLen":400,"time":88000,"type":0},{"id":0,"sLen":0,"time":89700,"type":0},{"id":3,"sLen":0,"time":89800,"type":0},{"id":2,"sLen":0,"time":90000,"type":0},{"id":3,"sLen":0,"time":90100,"type":0},{"id":0,"sLen":0,"time":90200,"type":0},{"id":1,"sLen":0,"time":90300,"type":0},{"id":3,"sLen":0,"time":90400,"type":0},{"id":2,"sLen":0,"time":90500,"type":0},{"id":1,"sLen":0,"time":90600,"type":0},{"id":2,"sLen":0,"time":90800,"type":0},{"id":1,"sLen":0,"time":90900,"type":0},{"id":0,"sLen":0,"time":91000,"type":0},{"id":2,"sLen":400,"time":91200,"type":0}],"position":"dad","type":0,"characters":["b_parents-christmas"]},{"visible":true,"notes":[{"id":3,"sLen":0,"time":9800,"type":0},{"id":1,"sLen":0,"time":9900,"type":0},{"id":3,"sLen":0,"time":10000,"type":0},{"id":3,"sLen":0,"time":10400,"type":0},{"id":3,"sLen":0,"time":10600,"type":0},{"id":0,"sLen":0,"time":10800,"type":0},{"id":2,"sLen":0,"time":11000,"type":0},{"id":3,"sLen":0,"time":11400,"type":0},{"id":0,"sLen":0,"time":11500,"type":0},{"id":3,"sLen":0,"time":11600,"type":0},{"id":3,"sLen":0,"time":11800,"type":0},{"id":1,"sLen":0,"time":12000,"type":0},{"id":2,"sLen":0,"time":12200,"type":0},{"id":0,"sLen":0,"time":12300,"type":0},{"id":3,"sLen":0,"time":12400,"type":0},{"id":2,"sLen":0,"time":12600,"type":0},{"id":3,"sLen":0,"time":13000,"type":0},{"id":1,"sLen":0,"time":13100,"type":0},{"id":3,"sLen":0,"time":13200,"type":0},{"id":3,"sLen":0,"time":13600,"type":0},{"id":3,"sLen":0,"time":13800,"type":0},{"id":0,"sLen":0,"time":14000,"type":0},{"id":2,"sLen":0,"time":14200,"type":0},{"id":3,"sLen":0,"time":14600,"type":0},{"id":0,"sLen":0,"time":14700,"type":0},{"id":3,"sLen":0,"time":14800,"type":0},{"id":3,"sLen":0,"time":15000,"type":0},{"id":1,"sLen":0,"time":15200,"type":0},{"id":2,"sLen":0,"time":15400,"type":0},{"id":0,"sLen":0,"time":15500,"type":0},{"id":3,"sLen":0,"time":15600,"type":0},{"id":2,"sLen":0,"time":15800,"type":0},{"id":2,"sLen":0,"time":22400,"type":0},{"id":0,"sLen":0,"time":22500,"type":0},{"id":2,"sLen":0,"time":22600,"type":0},{"id":0,"sLen":0,"time":22700,"type":0},{"id":1,"sLen":0,"time":22800,"type":0},{"id":3,"sLen":300,"time":22900,"type":0},{"id":0,"sLen":400,"time":23200,"type":0},{"id":1,"sLen":0,"time":23600,"type":0},{"id":3,"sLen":0,"time":23800,"type":0},{"id":3,"sLen":0,"time":24000,"type":0},{"id":2,"sLen":0,"time":24200,"type":0},{"id":2,"sLen":0,"time":24600,"type":0},{"id":2,"sLen":0,"time":25000,"type":0},{"id":0,"sLen":0,"time":25100,"type":0},{"id":1,"sLen":0,"time":25200,"type":0},{"id":3,"sLen":600,"time":25400,"type":0},{"id":2,"sLen":0,"time":26000,"type":0},{"id":1,"sLen":0,"time":26400,"type":0},{"id":1,"sLen":0,"time":26600,"type":0},{"id":3,"sLen":0,"time":26800,"type":0},{"id":0,"sLen":300,"time":27000,"type":0},{"id":0,"sLen":0,"time":27400,"type":0},{"id":3,"sLen":0,"time":27800,"type":0},{"id":1,"sLen":0,"time":27900,"type":0},{"id":3,"sLen":0,"time":28000,"type":0},{"id":3,"sLen":0,"time":28200,"type":0},{"id":2,"sLen":400,"time":28400,"type":0},{"id":0,"sLen":400,"time":28800,"type":0},{"id":2,"sLen":0,"time":35400,"type":0},{"id":0,"sLen":0,"time":35600,"type":0},{"id":1,"sLen":0,"time":35800,"type":0},{"id":2,"sLen":0,"time":35900,"type":0},{"id":3,"sLen":0,"time":36000,"type":0},{"id":0,"sLen":0,"time":36100,"type":0},{"id":1,"sLen":0,"time":36200,"type":0},{"id":0,"sLen":0,"time":36400,"type":0},{"id":1,"sLen":0,"time":36600,"type":0},{"id":2,"sLen":0,"time":36700,"type":0},{"id":3,"sLen":0,"time":36800,"type":0},{"id":0,"sLen":0,"time":36900,"type":0},{"id":1,"sLen":0,"time":37000,"type":0},{"id":0,"sLen":0,"time":37200,"type":0},{"id":1,"sLen":0,"time":37400,"type":0},{"id":2,"sLen":0,"time":37500,"type":0},{"id":3,"sLen":0,"time":37600,"type":0},{"id":0,"sLen":0,"time":37700,"type":0},{"id":1,"sLen":0,"time":37800,"type":0},{"id":3,"sLen":0,"time":38000,"type":0},{"id":2,"sLen":0,"time":38100,"type":0},{"id":1,"sLen":0,"time":38200,"type":0},{"id":2,"sLen":0,"time":38400,"type":0},{"id":2,"sLen":0,"time":38600,"type":0},{"id":0,"sLen":0,"time":38800,"type":0},{"id":1,"sLen":0,"time":39000,"type":0},{"id":2,"sLen":0,"time":39100,"type":0},{"id":3,"sLen":0,"time":39200,"type":0},{"id":0,"sLen":0,"time":39300,"type":0},{"id":1,"sLen":0,"time":39400,"type":0},{"id":0,"sLen":0,"time":39600,"type":0},{"id":1,"sLen":0,"time":39800,"type":0},{"id":2,"sLen":0,"time":39900,"type":0},{"id":3,"sLen":0,"time":40000,"type":0},{"id":0,"sLen":0,"time":40100,"type":0},{"id":1,"sLen":0,"time":40200,"type":0},{"id":0,"sLen":0,"time":40400,"type":0},{"id":3,"sLen":0,"time":40600,"type":0},{"id":0,"sLen":0,"time":40800,"type":0},{"id":2,"sLen":0,"time":40900,"type":0},{"id":3,"sLen":0,"time":41000,"type":0},{"id":1,"sLen":0,"time":41100,"type":0},{"id":2,"sLen":0,"time":41200,"type":0},{"id":3,"sLen":0,"time":41300,"type":0},{"id":0,"sLen":0,"time":41400,"type":0},{"id":2,"sLen":400,"time":41600,"type":0},{"id":0,"sLen":0,"time":43300,"type":0},{"id":3,"sLen":0,"time":43400,"type":0},{"id":2,"sLen":0,"time":43600,"type":0},{"id":0,"sLen":0,"time":43800,"type":0},{"id":3,"sLen":0,"time":44000,"type":0},{"id":2,"sLen":0,"time":44100,"type":0},{"id":1,"sLen":0,"time":44200,"type":0},{"id":2,"sLen":0,"time":44400,"type":0},{"id":1,"sLen":0,"time":44500,"type":0},{"id":0,"sLen":0,"time":44600,"type":0},{"id":2,"sLen":400,"time":44800,"type":0},{"id":0,"sLen":0,"time":46500,"type":0},{"id":3,"sLen":0,"time":46600,"type":0},{"id":2,"sLen":0,"time":46800,"type":0},{"id":3,"sLen":0,"time":46900,"type":0},{"id":0,"sLen":0,"time":47000,"type":0},{"id":1,"sLen":0,"time":47100,"type":0},{"id":3,"sLen":0,"time":47200,"type":0},{"id":2,"sLen":0,"time":47300,"type":0},{"id":1,"sLen":0,"time":47400,"type":0},{"id":2,"sLen":0,"time":47600,"type":0},{"id":1,"sLen":0,"time":47700,"type":0},{"id":0,"sLen":0,"time":47800,"type":0},{"id":2,"sLen":400,"time":48000,"type":0},{"id":3,"sLen":0,"time":54600,"type":0},{"id":0,"sLen":0,"time":54700,"type":0},{"id":3,"sLen":0,"time":54800,"type":0},{"id":3,"sLen":0,"time":55200,"type":0},{"id":1,"sLen":0,"time":55300,"type":0},{"id":3,"sLen":0,"time":55400,"type":0},{"id":3,"sLen":0,"time":55600,"type":0},{"id":2,"sLen":0,"time":55700,"type":0},{"id":0,"sLen":0,"time":55800,"type":0},{"id":1,"sLen":0,"time":55900,"type":0},{"id":3,"sLen":0,"time":56200,"type":0},{"id":0,"sLen":0,"time":56300,"type":0},{"id":3,"sLen":0,"time":56400,"type":0},{"id":3,"sLen":0,"time":56600,"type":0},{"id":1,"sLen":0,"time":56800,"type":0},{"id":0,"sLen":0,"time":56900,"type":0},{"id":1,"sLen":0,"time":57000,"type":0},{"id":3,"sLen":0,"time":57200,"type":0},{"id":2,"sLen":0,"time":57300,"type":0},{"id":0,"sLen":0,"time":57400,"type":0},{"id":3,"sLen":0,"time":57800,"type":0},{"id":0,"sLen":0,"time":57900,"type":0},{"id":3,"sLen":0,"time":58000,"type":0},{"id":3,"sLen":0,"time":58400,"type":0},{"id":1,"sLen":0,"time":58500,"type":0},{"id":3,"sLen":0,"time":58600,"type":0},{"id":3,"sLen":0,"time":58800,"type":0},{"id":2,"sLen":0,"time":58900,"type":0},{"id":0,"sLen":0,"time":59000,"type":0},{"id":1,"sLen":0,"time":59100,"type":0},{"id":3,"sLen":0,"time":59400,"type":0},{"id":0,"sLen":0,"time":59500,"type":0},{"id":3,"sLen":0,"time":59600,"type":0},{"id":3,"sLen":0,"time":59800,"type":0},{"id":1,"sLen":0,"time":60000,"type":0},{"id":0,"sLen":0,"time":60100,"type":0},{"id":1,"sLen":0,"time":60200,"type":0},{"id":3,"sLen":0,"time":60400,"type":0},{"id":2,"sLen":0,"time":60500,"type":0},{"id":0,"sLen":0,"time":60600,"type":0},{"id":0,"sLen":0,"time":64000,"type":0},{"id":3,"sLen":0,"time":64100,"type":0},{"id":2,"sLen":0,"time":64200,"type":0},{"id":3,"sLen":0,"time":64400,"type":0},{"id":1,"sLen":0,"time":64500,"type":0},{"id":0,"sLen":0,"time":64600,"type":0},{"id":3,"sLen":0,"time":64800,"type":0},{"id":0,"sLen":0,"time":65000,"type":0},{"id":1,"sLen":0,"time":65200,"type":0},{"id":2,"sLen":0,"time":65400,"type":0},{"id":0,"sLen":0,"time":65600,"type":0},{"id":3,"sLen":0,"time":65700,"type":0},{"id":2,"sLen":0,"time":65800,"type":0},{"id":1,"sLen":0,"time":66000,"type":0},{"id":2,"sLen":0,"time":66100,"type":0},{"id":3,"sLen":0,"time":66200,"type":0},{"id":0,"sLen":0,"time":66400,"type":0},{"id":2,"sLen":0,"time":66600,"type":0},{"id":0,"sLen":400,"time":66800,"type":0},{"id":1,"sLen":0,"time":70400,"type":0},{"id":1,"sLen":0,"time":70500,"type":0},{"id":2,"sLen":0,"time":70600,"type":0},{"id":3,"sLen":0,"time":70800,"type":0},{"id":0,"sLen":0,"time":71000,"type":0},{"id":2,"sLen":0,"time":71200,"type":0},{"id":0,"sLen":0,"time":71400,"type":0},{"id":1,"sLen":0,"time":71600,"type":0},{"id":0,"sLen":0,"time":71700,"type":0},{"id":1,"sLen":0,"time":71800,"type":0},{"id":3,"sLen":0,"time":71900,"type":0},{"id":0,"sLen":0,"time":72000,"type":0},{"id":3,"sLen":0,"time":72100,"type":0},{"id":1,"sLen":0,"time":72200,"type":0},{"id":2,"sLen":0,"time":72400,"type":0},{"id":0,"sLen":0,"time":72500,"type":0},{"id":2,"sLen":0,"time":72600,"type":0},{"id":3,"sLen":0,"time":72700,"type":0},{"id":1,"sLen":0,"time":72800,"type":0},{"id":2,"sLen":0,"time":72900,"type":0},{"id":0,"sLen":0,"time":73000,"type":0},{"id":2,"sLen":300,"time":73200,"type":0},{"id":2,"sLen":0,"time":73600,"type":0},{"id":0,"sLen":0,"time":73700,"type":0},{"id":2,"sLen":0,"time":73800,"type":0},{"id":0,"sLen":0,"time":73900,"type":0},{"id":1,"sLen":0,"time":74000,"type":0},{"id":3,"sLen":300,"time":74100,"type":0},{"id":0,"sLen":400,"time":74400,"type":0},{"id":1,"sLen":0,"time":74800,"type":0},{"id":3,"sLen":0,"time":75000,"type":0},{"id":3,"sLen":0,"time":75200,"type":0},{"id":2,"sLen":0,"time":75400,"type":0},{"id":2,"sLen":0,"time":75800,"type":0},{"id":2,"sLen":0,"time":76200,"type":0},{"id":0,"sLen":0,"time":76300,"type":0},{"id":1,"sLen":0,"time":76400,"type":0},{"id":3,"sLen":600,"time":76600,"type":0},{"id":2,"sLen":0,"time":77200,"type":0},{"id":1,"sLen":0,"time":77600,"type":0},{"id":1,"sLen":0,"time":77800,"type":0},{"id":3,"sLen":0,"time":78000,"type":0},{"id":0,"sLen":300,"time":78200,"type":0},{"id":0,"sLen":0,"time":78600,"type":0},{"id":3,"sLen":0,"time":79000,"type":0},{"id":1,"sLen":0,"time":79100,"type":0},{"id":3,"sLen":0,"time":79200,"type":0},{"id":3,"sLen":0,"time":79400,"type":0},{"id":2,"sLen":400,"time":79600,"type":0},{"id":0,"sLen":0,"time":80000,"type":0},{"id":2,"sLen":0,"time":80200,"type":0},{"id":0,"sLen":0,"time":80400,"type":0},{"id":1,"sLen":0,"time":80600,"type":0},{"id":2,"sLen":0,"time":80700,"type":0},{"id":3,"sLen":0,"time":80800,"type":0},{"id":0,"sLen":0,"time":80900,"type":0},{"id":1,"sLen":0,"time":81000,"type":0},{"id":0,"sLen":0,"time":81200,"type":0},{"id":1,"sLen":0,"time":81400,"type":0},{"id":2,"sLen":0,"time":81500,"type":0},{"id":3,"sLen":0,"time":81600,"type":0},{"id":0,"sLen":0,"time":81700,"type":0},{"id":1,"sLen":0,"time":81800,"type":0},{"id":0,"sLen":0,"time":82000,"type":0},{"id":1,"sLen":0,"time":82200,"type":0},{"id":2,"sLen":0,"time":82300,"type":0},{"id":3,"sLen":0,"time":82400,"type":0},{"id":0,"sLen":0,"time":82500,"type":0},{"id":1,"sLen":0,"time":82600,"type":0},{"id":3,"sLen":0,"time":82800,"type":0},{"id":2,"sLen":0,"time":82900,"type":0},{"id":1,"sLen":0,"time":83000,"type":0},{"id":2,"sLen":0,"time":83200,"type":0},{"id":2,"sLen":0,"time":83400,"type":0},{"id":0,"sLen":0,"time":83600,"type":0},{"id":1,"sLen":0,"time":83800,"type":0},{"id":2,"sLen":0,"time":83900,"type":0},{"id":3,"sLen":0,"time":84000,"type":0},{"id":0,"sLen":0,"time":84100,"type":0},{"id":1,"sLen":0,"time":84200,"type":0},{"id":0,"sLen":0,"time":84400,"type":0},{"id":1,"sLen":0,"time":84600,"type":0},{"id":2,"sLen":0,"time":84700,"type":0},{"id":3,"sLen":0,"time":84800,"type":0},{"id":0,"sLen":0,"time":84900,"type":0},{"id":1,"sLen":0,"time":85000,"type":0},{"id":0,"sLen":0,"time":85200,"type":0},{"id":3,"sLen":0,"time":85400,"type":0},{"id":0,"sLen":0,"time":85600,"type":0},{"id":2,"sLen":0,"time":85700,"type":0},{"id":3,"sLen":0,"time":85800,"type":0},{"id":1,"sLen":0,"time":85900,"type":0},{"id":2,"sLen":0,"time":86000,"type":0},{"id":3,"sLen":0,"time":86100,"type":0},{"id":0,"sLen":0,"time":86200,"type":0},{"id":2,"sLen":400,"time":86400,"type":0},{"id":0,"sLen":0,"time":88100,"type":0},{"id":3,"sLen":0,"time":88200,"type":0},{"id":2,"sLen":0,"time":88400,"type":0},{"id":0,"sLen":0,"time":88600,"type":0},{"id":3,"sLen":0,"time":88800,"type":0},{"id":2,"sLen":0,"time":88900,"type":0},{"id":1,"sLen":0,"time":89000,"type":0},{"id":2,"sLen":0,"time":89200,"type":0},{"id":1,"sLen":0,"time":89300,"type":0},{"id":0,"sLen":0,"time":89400,"type":0},{"id":2,"sLen":400,"time":89600,"type":0},{"id":0,"sLen":0,"time":91300,"type":0},{"id":3,"sLen":0,"time":91400,"type":0},{"id":2,"sLen":0,"time":91600,"type":0},{"id":3,"sLen":0,"time":91700,"type":0},{"id":0,"sLen":0,"time":91800,"type":0},{"id":1,"sLen":0,"time":91900,"type":0},{"id":3,"sLen":0,"time":92000,"type":0},{"id":2,"sLen":0,"time":92100,"type":0},{"id":1,"sLen":0,"time":92200,"type":0},{"id":2,"sLen":0,"time":92400,"type":0},{"id":1,"sLen":0,"time":92500,"type":0},{"id":0,"sLen":0,"time":92600,"type":0},{"id":2,"sLen":800,"time":92800,"type":0}],"position":"boyfriend","type":1,"characters":["b_bf-christmas"]},{"notes":[],"visible":false,"position":"girlfriend","type":2,"characters":["b_gf-christmas"]}],"codenameChart":true,"stage":"mall","noteTypes":[]}