{"events":[{"params":[1],"time":0,"name":"Camera Movement"},{"params":[0],"time":10434.7826086957,"name":"Camera Movement"},{"params":[1],"time":13043.4782608696,"name":"Camera Movement"},{"params":[0],"time":15652.1739130435,"name":"Camera Movement"},{"params":[1],"time":18260.8695652174,"name":"Camera Movement"},{"params":[0],"time":20869.5652173913,"name":"Camera Movement"},{"params":[1],"time":26086.9565217391,"name":"Camera Movement"},{"params":[0],"time":31304.3478260869,"name":"Camera Movement"},{"params":[1],"time":36521.7391304348,"name":"Camera Movement"},{"params":[0],"time":41739.1304347826,"name":"Camera Movement"},{"params":[1],"time":46956.5217391305,"name":"Camera Movement"},{"params":[0],"time":52173.9130434783,"name":"Camera Movement"},{"params":[1],"time":57391.3043478261,"name":"Camera Movement"},{"params":[0],"time":62608.695652174,"name":"Camera Movement"},{"params":[1],"time":67826.0869565218,"name":"Camera Movement"},{"params":[0],"time":73043.4782608697,"name":"Camera Movement"},{"params":[1],"time":78260.8695652175,"name":"Camera Movement"}],"scrollSpeed":2.2,"codenameChart":true,"strumLines":[{"strumScale":1,"position":"dad","notes":[{"id":1,"sLen":0,"time":10434.7826086957,"type":0},{"id":1,"sLen":0,"time":10760.8695652174,"type":0},{"id":1,"sLen":0,"time":15652.1739130435,"type":0},{"id":1,"sLen":0,"time":15978.2608695652,"type":0},{"id":2,"sLen":0,"time":20869.5652173913,"type":0},{"id":2,"sLen":162.999999999996,"time":21195.652173913,"type":0},{"id":0,"sLen":0,"time":21358.6956521739,"type":0},{"id":0,"sLen":0,"time":21521.7391304348,"type":0},{"id":2,"sLen":0,"time":21684.7826086957,"type":0},{"id":3,"sLen":0,"time":21847.8260869565,"type":0},{"id":1,"sLen":0,"time":22010.8695652174,"type":0},{"id":3,"sLen":0,"time":22173.9130434783,"type":0},{"id":0,"sLen":0,"time":22500,"type":0},{"id":3,"sLen":0,"time":22826.0869565217,"type":0},{"id":0,"sLen":0,"time":22989.1304347826,"type":0},{"id":0,"sLen":326,"time":23152.1739130435,"type":0},{"id":0,"sLen":0,"time":23478.2608695652,"type":0},{"id":1,"sLen":0,"time":23559.7826086957,"type":0},{"id":0,"sLen":0,"time":23641.3043478261,"type":0},{"id":0,"sLen":245.000000000004,"time":23804.347826087,"type":0},{"id":1,"sLen":0,"time":24130.4347826087,"type":0},{"id":3,"sLen":0,"time":24293.4782608696,"type":0},{"id":0,"sLen":0,"time":24456.5217391304,"type":0},{"id":2,"sLen":0,"time":24619.5652173913,"type":0},{"id":0,"sLen":0,"time":24701.0869565217,"type":0},{"id":2,"sLen":245.000000000004,"time":24782.6086956522,"type":0},{"id":2,"sLen":244.999999999993,"time":25108.6956521739,"type":0},{"id":3,"sLen":245,"time":25434.7826086957,"type":0},{"id":1,"sLen":0,"time":25760.8695652174,"type":0},{"id":0,"sLen":162.999999999996,"time":25923.9130434783,"type":0},{"id":3,"sLen":0,"time":31304.347826087,"type":0},{"id":2,"sLen":0,"time":31467.3913043478,"type":0},{"id":0,"sLen":0,"time":31630.4347826087,"type":0},{"id":0,"sLen":0,"time":31793.4782608696,"type":0},{"id":1,"sLen":0,"time":31875,"type":0},{"id":2,"sLen":0,"time":31956.5217391304,"type":0},{"id":3,"sLen":0,"time":32119.5652173913,"type":0},{"id":2,"sLen":0,"time":32282.6086956522,"type":0},{"id":0,"sLen":0,"time":32445.652173913,"type":0},{"id":3,"sLen":0,"time":32608.6956521739,"type":0},{"id":3,"sLen":0,"time":32934.7826086956,"type":0},{"id":3,"sLen":0,"time":33260.8695652174,"type":0},{"id":0,"sLen":0,"time":33342.3913043478,"type":0},{"id":3,"sLen":0,"time":33423.9130434783,"type":0},{"id":3,"sLen":0,"time":33586.9565217391,"type":0},{"id":0,"sLen":0,"time":33913.0434782609,"type":0},{"id":1,"sLen":0,"time":34076.0869565217,"type":0},{"id":2,"sLen":0,"time":34239.1304347826,"type":0},{"id":0,"sLen":0,"time":34402.1739130435,"type":0},{"id":2,"sLen":0,"time":34483.6956521739,"type":0},{"id":3,"sLen":0,"time":34565.2173913043,"type":0},{"id":2,"sLen":0,"time":34728.2608695652,"type":0},{"id":1,"sLen":0,"time":34891.3043478261,"type":0},{"id":0,"sLen":0,"time":35054.347826087,"type":0},{"id":1,"sLen":0,"time":35217.3913043478,"type":0},{"id":1,"sLen":0,"time":35380.4347826087,"type":0},{"id":1,"sLen":0,"time":35543.4782608696,"type":0},{"id":3,"sLen":163,"time":35706.5217391304,"type":0},{"id":2,"sLen":0,"time":35869.5652173913,"type":0},{"id":0,"sLen":0,"time":36032.6086956522,"type":0},{"id":0,"sLen":0,"time":36114.1304347826,"type":0},{"id":2,"sLen":0,"time":36195.652173913,"type":0},{"id":1,"sLen":0,"time":36358.6956521739,"type":0},{"id":2,"sLen":0,"time":41739.1304347826,"type":0},{"id":3,"sLen":0,"time":41902.1739130435,"type":0},{"id":0,"sLen":0,"time":42065.2173913043,"type":0},{"id":2,"sLen":0,"time":42228.2608695652,"type":0},{"id":3,"sLen":0,"time":42391.3043478261,"type":0},{"id":0,"sLen":0,"time":42554.347826087,"type":0},{"id":2,"sLen":0,"time":42717.3913043478,"type":0},{"id":3,"sLen":0,"time":42880.4347826087,"type":0},{"id":0,"sLen":0,"time":43043.4782608696,"type":0},{"id":2,"sLen":0,"time":43206.5217391304,"type":0},{"id":3,"sLen":0,"time":43369.5652173913,"type":0},{"id":0,"sLen":0,"time":43532.6086956522,"type":0},{"id":0,"sLen":0,"time":43695.652173913,"type":0},{"id":3,"sLen":0,"time":43858.6956521739,"type":0},{"id":0,"sLen":245,"time":44021.7391304348,"type":0},{"id":2,"sLen":0,"time":44347.8260869565,"type":0},{"id":3,"sLen":0,"time":44510.8695652174,"type":0},{"id":0,"sLen":0,"time":44673.9130434783,"type":0},{"id":2,"sLen":0,"time":44836.9565217391,"type":0},{"id":3,"sLen":0,"time":45000,"type":0},{"id":0,"sLen":0,"time":45163.0434782609,"type":0},{"id":2,"sLen":0,"time":45326.0869565217,"type":0},{"id":3,"sLen":0,"time":45489.1304347826,"type":0},{"id":0,"sLen":0,"time":45652.1739130435,"type":0},{"id":0,"sLen":0,"time":45815.2173913043,"type":0},{"id":1,"sLen":0,"time":45896.7391304348,"type":0},{"id":3,"sLen":0,"time":45978.2608695652,"type":0},{"id":0,"sLen":0,"time":46141.3043478261,"type":0},{"id":2,"sLen":0,"time":46304.347826087,"type":0},{"id":3,"sLen":0,"time":46467.3913043478,"type":0},{"id":1,"sLen":163,"time":46630.4347826087,"type":0},{"id":0,"sLen":0,"time":46793.4782608696,"type":0},{"id":0,"sLen":245,"time":52173.9130434783,"type":0},{"id":3,"sLen":0,"time":52418.4782608696,"type":0},{"id":0,"sLen":0,"time":52500,"type":0},{"id":2,"sLen":0,"time":52663.0434782609,"type":0},{"id":2,"sLen":0,"time":52826.0869565217,"type":0},{"id":1,"sLen":0,"time":52989.1304347826,"type":0},{"id":0,"sLen":0,"time":53152.1739130435,"type":0},{"id":3,"sLen":0,"time":53233.6956521739,"type":0},{"id":1,"sLen":0,"time":53315.2173913043,"type":0},{"id":2,"sLen":0,"time":53478.2608695652,"type":0},{"id":0,"sLen":0,"time":53641.3043478261,"type":0},{"id":1,"sLen":0,"time":53804.347826087,"type":0},{"id":1,"sLen":0,"time":53885.8695652174,"type":0},{"id":2,"sLen":0,"time":53967.3913043478,"type":0},{"id":2,"sLen":0,"time":54130.4347826087,"type":0},{"id":3,"sLen":0,"time":54293.4782608696,"type":0},{"id":0,"sLen":163,"time":54456.5217391304,"type":0},{"id":1,"sLen":0,"time":54619.5652173913,"type":0},{"id":2,"sLen":0,"time":54782.6086956522,"type":0},{"id":3,"sLen":0,"time":54864.1304347826,"type":0},{"id":0,"sLen":0,"time":54945.652173913,"type":0},{"id":1,"sLen":0,"time":55108.6956521739,"type":0},{"id":3,"sLen":0,"time":55271.7391304348,"type":0},{"id":2,"sLen":0,"time":55434.7826086956,"type":0},{"id":3,"sLen":0,"time":55516.3043478261,"type":0},{"id":0,"sLen":0,"time":55597.8260869565,"type":0},{"id":2,"sLen":0,"time":55760.8695652174,"type":0},{"id":3,"sLen":0,"time":55842.3913043478,"type":0},{"id":0,"sLen":0,"time":55923.9130434783,"type":0},{"id":0,"sLen":0,"time":56086.9565217391,"type":0},{"id":0,"sLen":0,"time":56250,"type":0},{"id":2,"sLen":0,"time":56331.5217391304,"type":0},{"id":1,"sLen":0,"time":56413.0434782609,"type":0},{"id":2,"sLen":0,"time":56494.5652173913,"type":0},{"id":3,"sLen":0,"time":56576.0869565217,"type":0},{"id":2,"sLen":0,"time":56739.1304347826,"type":0},{"id":2,"sLen":0,"time":56902.1739130435,"type":0},{"id":0,"sLen":163,"time":57065.2173913043,"type":0},{"id":3,"sLen":0,"time":57228.2608695652,"type":0},{"id":0,"sLen":0,"time":61956.5217391304,"type":0},{"id":2,"sLen":0,"time":62119.5652173913,"type":0},{"id":3,"sLen":0,"time":62282.6086956522,"type":0},{"id":1,"sLen":0,"time":62445.652173913,"type":0},{"id":2,"sLen":0,"time":62608.6956521739,"type":0},{"id":2,"sLen":163,"time":62934.7826086956,"type":0},{"id":0,"sLen":0,"time":63097.8260869565,"type":0},{"id":0,"sLen":0,"time":63260.8695652174,"type":0},{"id":2,"sLen":0,"time":63423.9130434783,"type":0},{"id":3,"sLen":0,"time":63586.9565217391,"type":0},{"id":1,"sLen":0,"time":63750,"type":0},{"id":3,"sLen":0,"time":63913.0434782609,"type":0},{"id":0,"sLen":0,"time":64239.1304347826,"type":0},{"id":3,"sLen":0,"time":64565.2173913043,"type":0},{"id":0,"sLen":0,"time":64728.2608695652,"type":0},{"id":0,"sLen":326.000000000007,"time":64891.3043478261,"type":0},{"id":0,"sLen":0,"time":65217.3913043478,"type":0},{"id":1,"sLen":0,"time":65298.9130434783,"type":0},{"id":0,"sLen":0,"time":65380.4347826087,"type":0},{"id":0,"sLen":245,"time":65543.4782608696,"type":0},{"id":1,"sLen":0,"time":65869.5652173913,"type":0},{"id":3,"sLen":0,"time":66032.6086956522,"type":0},{"id":0,"sLen":0,"time":66195.652173913,"type":0},{"id":2,"sLen":0,"time":66358.6956521739,"type":0},{"id":0,"sLen":0,"time":66440.2173913043,"type":0},{"id":2,"sLen":245,"time":66521.7391304348,"type":0},{"id":2,"sLen":245,"time":66847.8260869565,"type":0},{"id":3,"sLen":245,"time":67173.9130434783,"type":0},{"id":1,"sLen":0,"time":67500,"type":0},{"id":0,"sLen":163,"time":67663.0434782609,"type":0},{"id":3,"sLen":0,"time":73043.4782608696,"type":0},{"id":2,"sLen":0,"time":73206.5217391304,"type":0},{"id":0,"sLen":0,"time":73369.5652173913,"type":0},{"id":0,"sLen":0,"time":73532.6086956522,"type":0},{"id":1,"sLen":0,"time":73614.1304347826,"type":0},{"id":2,"sLen":0,"time":73695.652173913,"type":0},{"id":3,"sLen":0,"time":73858.6956521739,"type":0},{"id":2,"sLen":0,"time":74021.7391304348,"type":0},{"id":0,"sLen":0,"time":74184.7826086956,"type":0},{"id":3,"sLen":0,"time":74347.8260869565,"type":0},{"id":3,"sLen":0,"time":74673.9130434783,"type":0},{"id":3,"sLen":0,"time":75000,"type":0},{"id":0,"sLen":0,"time":75081.5217391304,"type":0},{"id":3,"sLen":0,"time":75163.0434782609,"type":0},{"id":3,"sLen":0,"time":75326.0869565217,"type":0},{"id":0,"sLen":0,"time":75652.1739130435,"type":0},{"id":1,"sLen":0,"time":75815.2173913043,"type":0},{"id":2,"sLen":0,"time":75978.2608695652,"type":0},{"id":0,"sLen":0,"time":76141.3043478261,"type":0},{"id":2,"sLen":0,"time":76222.8260869565,"type":0},{"id":3,"sLen":0,"time":76304.347826087,"type":0},{"id":2,"sLen":0,"time":76467.3913043478,"type":0},{"id":1,"sLen":0,"time":76630.4347826087,"type":0},{"id":0,"sLen":0,"time":76793.4782608696,"type":0},{"id":1,"sLen":0,"time":76956.5217391304,"type":0},{"id":1,"sLen":0,"time":77119.5652173913,"type":0},{"id":1,"sLen":0,"time":77282.6086956522,"type":0},{"id":3,"sLen":163,"time":77445.652173913,"type":0},{"id":2,"sLen":0,"time":77608.6956521739,"type":0},{"id":0,"sLen":0,"time":77771.7391304348,"type":0},{"id":0,"sLen":0,"time":77853.2608695652,"type":0},{"id":2,"sLen":0,"time":77934.7826086956,"type":0},{"id":1,"sLen":0,"time":78097.8260869565,"type":0}],"characters":["b_spooky"],"type":0,"visible":true,"strumPos":[96,50]},{"strumScale":1,"position":"boyfriend","notes":[{"id":2,"sLen":0,"time":13043.4782608696,"type":0},{"id":2,"sLen":0,"time":13369.5652173913,"type":0},{"id":2,"sLen":0,"time":18260.8695652174,"type":0},{"id":2,"sLen":0,"time":18586.9565217391,"type":0},{"id":2,"sLen":0,"time":19565.2173913043,"type":0},{"id":2,"sLen":0,"time":20054.347826087,"type":0},{"id":2,"sLen":0,"time":20217.3913043478,"type":0},{"id":2,"sLen":0,"time":20706.5217391304,"type":0},{"id":1,"sLen":0,"time":26086.9565217391,"type":0},{"id":1,"sLen":163,"time":26413.0434782609,"type":0},{"id":3,"sLen":0,"time":26576.0869565217,"type":0},{"id":3,"sLen":0,"time":26739.1304347826,"type":0},{"id":1,"sLen":0,"time":26902.1739130435,"type":0},{"id":0,"sLen":0,"time":27065.2173913043,"type":0},{"id":2,"sLen":0,"time":27228.2608695652,"type":0},{"id":0,"sLen":0,"time":27391.3043478261,"type":0},{"id":3,"sLen":0,"time":27717.3913043478,"type":0},{"id":0,"sLen":0,"time":28043.4782608696,"type":0},{"id":3,"sLen":0,"time":28206.5217391304,"type":0},{"id":3,"sLen":326,"time":28369.5652173913,"type":0},{"id":3,"sLen":0,"time":28695.652173913,"type":0},{"id":2,"sLen":0,"time":28777.1739130435,"type":0},{"id":3,"sLen":0,"time":28858.6956521739,"type":0},{"id":3,"sLen":244.999999999989,"time":29021.7391304348,"type":0},{"id":2,"sLen":0,"time":29347.8260869565,"type":0},{"id":0,"sLen":0,"time":29510.8695652174,"type":0},{"id":3,"sLen":0,"time":29673.9130434783,"type":0},{"id":1,"sLen":0,"time":29836.9565217391,"type":0},{"id":3,"sLen":0,"time":29918.4782608696,"type":0},{"id":1,"sLen":245,"time":30000,"type":0},{"id":1,"sLen":245.000000000004,"time":30326.0869565217,"type":0},{"id":0,"sLen":245.000000000004,"time":30652.1739130435,"type":0},{"id":2,"sLen":0,"time":30978.2608695652,"type":0},{"id":3,"sLen":162.999999999996,"time":31141.3043478261,"type":0},{"id":0,"sLen":0,"time":36521.7391304348,"type":0},{"id":1,"sLen":0,"time":36684.7826086956,"type":0},{"id":3,"sLen":0,"time":36847.8260869565,"type":0},{"id":3,"sLen":0,"time":37010.8695652174,"type":0},{"id":2,"sLen":0,"time":37092.3913043478,"type":0},{"id":1,"sLen":0,"time":37173.9130434783,"type":0},{"id":0,"sLen":0,"time":37336.9565217391,"type":0},{"id":1,"sLen":0,"time":37500,"type":0},{"id":3,"sLen":0,"time":37663.0434782609,"type":0},{"id":0,"sLen":0,"time":37826.0869565217,"type":0},{"id":0,"sLen":0,"time":38152.1739130435,"type":0},{"id":0,"sLen":0,"time":38478.2608695652,"type":0},{"id":3,"sLen":0,"time":38559.7826086956,"type":0},{"id":0,"sLen":0,"time":38641.3043478261,"type":0},{"id":0,"sLen":0,"time":38804.347826087,"type":0},{"id":3,"sLen":0,"time":39130.4347826087,"type":0},{"id":2,"sLen":0,"time":39293.4782608696,"type":0},{"id":1,"sLen":0,"time":39456.5217391304,"type":0},{"id":3,"sLen":0,"time":39619.5652173913,"type":0},{"id":1,"sLen":0,"time":39701.0869565217,"type":0},{"id":0,"sLen":0,"time":39782.6086956522,"type":0},{"id":1,"sLen":0,"time":39945.652173913,"type":0},{"id":2,"sLen":0,"time":40108.6956521739,"type":0},{"id":3,"sLen":0,"time":40271.7391304348,"type":0},{"id":2,"sLen":0,"time":40434.7826086956,"type":0},{"id":2,"sLen":0,"time":40597.8260869565,"type":0},{"id":2,"sLen":0,"time":40760.8695652174,"type":0},{"id":0,"sLen":163,"time":40923.9130434783,"type":0},{"id":1,"sLen":0,"time":41086.9565217391,"type":0},{"id":3,"sLen":0,"time":41250,"type":0},{"id":3,"sLen":0,"time":41331.5217391304,"type":0},{"id":1,"sLen":0,"time":41413.0434782609,"type":0},{"id":2,"sLen":0,"time":41576.0869565217,"type":0},{"id":1,"sLen":0,"time":46956.5217391304,"type":0},{"id":0,"sLen":0,"time":47119.5652173913,"type":0},{"id":3,"sLen":0,"time":47282.6086956522,"type":0},{"id":1,"sLen":0,"time":47445.652173913,"type":0},{"id":0,"sLen":0,"time":47608.6956521739,"type":0},{"id":3,"sLen":0,"time":47771.7391304348,"type":0},{"id":1,"sLen":0,"time":47934.7826086956,"type":0},{"id":0,"sLen":0,"time":48097.8260869565,"type":0},{"id":3,"sLen":0,"time":48260.8695652174,"type":0},{"id":1,"sLen":0,"time":48423.9130434783,"type":0},{"id":0,"sLen":0,"time":48586.9565217391,"type":0},{"id":3,"sLen":0,"time":48750,"type":0},{"id":3,"sLen":0,"time":48913.0434782609,"type":0},{"id":0,"sLen":0,"time":49076.0869565217,"type":0},{"id":3,"sLen":244.999999999993,"time":49239.1304347826,"type":0},{"id":1,"sLen":0,"time":49565.2173913043,"type":0},{"id":0,"sLen":0,"time":49728.2608695652,"type":0},{"id":3,"sLen":0,"time":49891.3043478261,"type":0},{"id":1,"sLen":0,"time":50054.347826087,"type":0},{"id":0,"sLen":0,"time":50217.3913043478,"type":0},{"id":3,"sLen":0,"time":50380.4347826087,"type":0},{"id":1,"sLen":0,"time":50543.4782608696,"type":0},{"id":0,"sLen":0,"time":50706.5217391304,"type":0},{"id":3,"sLen":0,"time":50869.5652173913,"type":0},{"id":3,"sLen":0,"time":51032.6086956522,"type":0},{"id":2,"sLen":0,"time":51114.1304347826,"type":0},{"id":0,"sLen":0,"time":51195.652173913,"type":0},{"id":3,"sLen":0,"time":51358.6956521739,"type":0},{"id":1,"sLen":0,"time":51521.7391304348,"type":0},{"id":0,"sLen":0,"time":51684.7826086956,"type":0},{"id":2,"sLen":162.999999999993,"time":51847.8260869565,"type":0},{"id":3,"sLen":0,"time":52010.8695652174,"type":0},{"id":3,"sLen":245.000000000007,"time":57391.3043478261,"type":0},{"id":0,"sLen":0,"time":57635.8695652174,"type":0},{"id":3,"sLen":0,"time":57717.3913043478,"type":0},{"id":1,"sLen":0,"time":57880.4347826087,"type":0},{"id":1,"sLen":0,"time":58043.4782608696,"type":0},{"id":2,"sLen":0,"time":58206.5217391304,"type":0},{"id":3,"sLen":0,"time":58369.5652173913,"type":0},{"id":0,"sLen":0,"time":58451.0869565217,"type":0},{"id":2,"sLen":0,"time":58532.6086956522,"type":0},{"id":1,"sLen":0,"time":58695.652173913,"type":0},{"id":3,"sLen":0,"time":58858.6956521739,"type":0},{"id":2,"sLen":0,"time":59021.7391304348,"type":0},{"id":2,"sLen":0,"time":59103.2608695652,"type":0},{"id":1,"sLen":0,"time":59184.7826086956,"type":0},{"id":1,"sLen":0,"time":59347.8260869565,"type":0},{"id":0,"sLen":0,"time":59510.8695652174,"type":0},{"id":3,"sLen":162.999999999993,"time":59673.9130434783,"type":0},{"id":2,"sLen":0,"time":59836.9565217391,"type":0},{"id":1,"sLen":0,"time":60000,"type":0},{"id":0,"sLen":0,"time":60081.5217391304,"type":0},{"id":3,"sLen":0,"time":60163.0434782609,"type":0},{"id":2,"sLen":0,"time":60326.0869565217,"type":0},{"id":0,"sLen":0,"time":60489.1304347826,"type":0},{"id":1,"sLen":0,"time":60652.1739130435,"type":0},{"id":0,"sLen":0,"time":60733.6956521739,"type":0},{"id":3,"sLen":0,"time":60815.2173913043,"type":0},{"id":1,"sLen":0,"time":60978.2608695652,"type":0},{"id":0,"sLen":0,"time":61059.7826086956,"type":0},{"id":3,"sLen":0,"time":61141.3043478261,"type":0},{"id":3,"sLen":0,"time":61304.347826087,"type":0},{"id":3,"sLen":0,"time":61467.3913043478,"type":0},{"id":1,"sLen":0,"time":61548.9130434783,"type":0},{"id":2,"sLen":0,"time":61630.4347826087,"type":0},{"id":1,"sLen":0,"time":61711.9565217391,"type":0},{"id":0,"sLen":0,"time":61793.4782608696,"type":0},{"id":1,"sLen":0,"time":61956.5217391304,"type":0},{"id":1,"sLen":0,"time":62119.5652173913,"type":0},{"id":3,"sLen":162.999999999993,"time":62282.6086956522,"type":0},{"id":0,"sLen":0,"time":62445.652173913,"type":0},{"id":3,"sLen":0,"time":67173.9130434783,"type":0},{"id":1,"sLen":0,"time":67336.9565217391,"type":0},{"id":0,"sLen":0,"time":67500,"type":0},{"id":2,"sLen":0,"time":67663.0434782609,"type":0},{"id":1,"sLen":0,"time":67826.0869565217,"type":0},{"id":1,"sLen":163,"time":68152.1739130435,"type":0},{"id":3,"sLen":0,"time":68315.2173913043,"type":0},{"id":3,"sLen":0,"time":68478.2608695652,"type":0},{"id":1,"sLen":0,"time":68641.3043478261,"type":0},{"id":0,"sLen":0,"time":68804.347826087,"type":0},{"id":2,"sLen":0,"time":68967.3913043478,"type":0},{"id":0,"sLen":0,"time":69130.4347826087,"type":0},{"id":3,"sLen":0,"time":69456.5217391304,"type":0},{"id":0,"sLen":0,"time":69782.6086956522,"type":0},{"id":3,"sLen":0,"time":69945.652173913,"type":0},{"id":3,"sLen":326,"time":70108.6956521739,"type":0},{"id":3,"sLen":0,"time":70434.7826086956,"type":0},{"id":2,"sLen":0,"time":70516.3043478261,"type":0},{"id":3,"sLen":0,"time":70597.8260869565,"type":0},{"id":3,"sLen":245,"time":70760.8695652174,"type":0},{"id":2,"sLen":0,"time":71086.9565217391,"type":0},{"id":0,"sLen":0,"time":71250,"type":0},{"id":3,"sLen":0,"time":71413.0434782609,"type":0},{"id":1,"sLen":0,"time":71576.0869565217,"type":0},{"id":3,"sLen":0,"time":71657.6086956522,"type":0},{"id":1,"sLen":245,"time":71739.1304347826,"type":0},{"id":1,"sLen":245,"time":72065.2173913043,"type":0},{"id":0,"sLen":245,"time":72391.3043478261,"type":0},{"id":2,"sLen":0,"time":72717.3913043478,"type":0},{"id":3,"sLen":163,"time":72880.4347826087,"type":0},{"id":0,"sLen":0,"time":78260.8695652174,"type":0},{"id":1,"sLen":0,"time":78423.9130434783,"type":0},{"id":3,"sLen":0,"time":78586.9565217391,"type":0},{"id":3,"sLen":0,"time":78750,"type":0},{"id":2,"sLen":0,"time":78831.5217391304,"type":0},{"id":1,"sLen":0,"time":78913.0434782609,"type":0},{"id":0,"sLen":0,"time":79076.0869565217,"type":0},{"id":1,"sLen":0,"time":79239.1304347826,"type":0},{"id":3,"sLen":0,"time":79402.1739130435,"type":0},{"id":0,"sLen":0,"time":79565.2173913043,"type":0},{"id":0,"sLen":0,"time":79891.3043478261,"type":0},{"id":0,"sLen":0,"time":80217.3913043478,"type":0},{"id":3,"sLen":0,"time":80298.9130434783,"type":0},{"id":0,"sLen":0,"time":80380.4347826087,"type":0},{"id":0,"sLen":0,"time":80543.4782608696,"type":0},{"id":3,"sLen":0,"time":80869.5652173913,"type":0},{"id":2,"sLen":0,"time":81032.6086956522,"type":0},{"id":1,"sLen":0,"time":81195.652173913,"type":0},{"id":3,"sLen":0,"time":81358.6956521739,"type":0},{"id":1,"sLen":0,"time":81440.2173913043,"type":0},{"id":0,"sLen":0,"time":81521.7391304348,"type":0},{"id":1,"sLen":0,"time":81684.7826086956,"type":0},{"id":2,"sLen":0,"time":81847.8260869565,"type":0},{"id":3,"sLen":0,"time":82010.8695652174,"type":0},{"id":2,"sLen":0,"time":82173.9130434783,"type":0},{"id":2,"sLen":0,"time":82336.9565217391,"type":0},{"id":2,"sLen":0,"time":82500,"type":0},{"id":0,"sLen":163,"time":82663.0434782609,"type":0},{"id":1,"sLen":0,"time":82826.0869565217,"type":0},{"id":3,"sLen":0,"time":82989.1304347826,"type":0},{"id":3,"sLen":0,"time":83070.652173913,"type":0},{"id":1,"sLen":0,"time":83152.1739130435,"type":0},{"id":2,"sLen":0,"time":83315.2173913043,"type":0},{"id":3,"sLen":0,"time":83478.2608695652,"type":0}],"characters":["b_bf"],"type":1,"visible":true,"strumPos":[736,50]},{"strumScale":1,"position":"girlfriend","notes":[],"characters":["b_gf"],"type":2,"visible":false,"strumPos":[96,50]}],"stage":"spooky","noteTypes":[]}